<annotation>
  <folder>bucket-dataset</folder>
  <filename>00331.jpg</filename>
  <size>
    <width>240</width>
    <height>180</height>
    <depth>3</depth>
  </size>
  <segmented>0</segmented>
  <object>
    <name>bucket</name>
    <pose>Unspecified</pose>
    <truncated>0</truncated>
    <difficult>0</difficult>
    <bndbox>
      <xmin>60.33333333333333</xmin>
      <ymin>50.955882352941174</ymin>
      <xmax>104</xmax>
      <ymax>101.58088235294116</ymax>
    </bndbox>
  </object>
  <object>
    <name>bucket</name>
    <pose>Unspecified</pose>
    <truncated>0</truncated>
    <difficult>0</difficult>
    <bndbox>
      <xmin>137.33333333333331</xmin>
      <ymin>51.61764705882353</ymin>
      <xmax>172</xmax>
      <ymax>93.63970588235296</ymax>
    </bndbox>
  </object>
</annotation>
