<annotation>
  <folder>bucket-dataset</folder>
  <filename>00485.jpg</filename>
  <size>
    <width>240</width>
    <height>180</height>
    <depth>3</depth>
  </size>
  <segmented>0</segmented>
  <object>
    <name>bucket</name>
    <pose>Unspecified</pose>
    <truncated>0</truncated>
    <difficult>0</difficult>
    <bndbox>
      <xmin>3.4999999999999996</xmin>
      <ymin>54.9264705882353</ymin>
      <xmax>64.5</xmax>
      <ymax>127.72058823529412</ymax>
    </bndbox>
  </object>
  <object>
    <name>bucket</name>
    <pose>Unspecified</pose>
    <truncated>0</truncated>
    <difficult>0</difficult>
    <bndbox>
      <xmin>100.5</xmin>
      <ymin>54.264705882352935</ymin>
      <xmax>130.83333333333331</xmax>
      <ymax>93.30882352941177</ymax>
    </bndbox>
  </object>
  <object>
    <name>bucket</name>
    <pose>Unspecified</pose>
    <truncated>0</truncated>
    <difficult>0</difficult>
    <bndbox>
      <xmin>222.16666666666666</xmin>
      <ymin>47.64705882352941</ymin>
      <xmax>239.5</xmax>
      <ymax>98.93382352941177</ymax>
    </bndbox>
  </object>
</annotation>
