<annotation>
  <folder>bucket-dataset</folder>
  <filename>00629.jpg</filename>
  <size>
    <width>240</width>
    <height>180</height>
    <depth>3</depth>
  </size>
  <segmented>0</segmented>
  <object>
    <name>bucket</name>
    <pose>Unspecified</pose>
    <truncated>0</truncated>
    <difficult>0</difficult>
    <bndbox>
      <xmin>86.5</xmin>
      <ymin>68.49264705882352</ymin>
      <xmax>122.16666666666666</xmax>
      <ymax>116.8014705882353</ymax>
    </bndbox>
  </object>
  <object>
    <name>bucket</name>
    <pose>Unspecified</pose>
    <truncated>0</truncated>
    <difficult>0</difficult>
    <bndbox>
      <xmin>130.16666666666666</xmin>
      <ymin>71.47058823529412</ymin>
      <xmax>160.5</xmax>
      <ymax>111.50735294117648</ymax>
    </bndbox>
  </object>
</annotation>
