<annotation>
  <folder>bucket-dataset</folder>
  <filename>00286.jpg</filename>
  <size>
    <width>240</width>
    <height>180</height>
    <depth>3</depth>
  </size>
  <segmented>0</segmented>
  <object>
    <name>bucket</name>
    <pose>Unspecified</pose>
    <truncated>0</truncated>
    <difficult>0</difficult>
    <bndbox>
      <xmin>16.833333333333332</xmin>
      <ymin>66.50735294117648</ymin>
      <xmax>34.49999999999999</xmax>
      <ymax>86.69117647058823</ymax>
    </bndbox>
  </object>
  <object>
    <name>bucket</name>
    <pose>Unspecified</pose>
    <truncated>0</truncated>
    <difficult>0</difficult>
    <bndbox>
      <xmin>76.16666666666666</xmin>
      <ymin>55.58823529411765</ymin>
      <xmax>104.49999999999999</xmax>
      <ymax>91.98529411764706</ymax>
    </bndbox>
  </object>
</annotation>
