<annotation>
  <folder>bucket-dataset</folder>
  <filename>00593.jpg</filename>
  <size>
    <width>240</width>
    <height>180</height>
    <depth>3</depth>
  </size>
  <segmented>0</segmented>
  <object>
    <name>bucket</name>
    <pose>Unspecified</pose>
    <truncated>0</truncated>
    <difficult>0</difficult>
    <bndbox>
      <xmin>121.5</xmin>
      <ymin>63.529411764705884</ymin>
      <xmax>148.16666666666669</xmax>
      <ymax>97.94117647058823</ymax>
    </bndbox>
  </object>
  <object>
    <name>bucket</name>
    <pose>Unspecified</pose>
    <truncated>0</truncated>
    <difficult>0</difficult>
    <bndbox>
      <xmin>159.16666666666666</xmin>
      <ymin>61.875</ymin>
      <xmax>190.83333333333331</xmax>
      <ymax>101.58088235294116</ymax>
    </bndbox>
  </object>
  <object>
    <name>bucket</name>
    <pose>Unspecified</pose>
    <truncated>0</truncated>
    <difficult>0</difficult>
    <bndbox>
      <xmin>191.16666666666666</xmin>
      <ymin>60.5514705882353</ymin>
      <xmax>222.16666666666666</xmax>
      <ymax>96.28676470588235</ymax>
    </bndbox>
  </object>
</annotation>
