<annotation>
  <folder>bucket-dataset</folder>
  <filename>00253.jpg</filename>
  <size>
    <width>240</width>
    <height>180</height>
    <depth>3</depth>
  </size>
  <segmented>0</segmented>
  <object>
    <name>bucket</name>
    <pose>Unspecified</pose>
    <truncated>0</truncated>
    <difficult>0</difficult>
    <bndbox>
      <xmin>104</xmin>
      <ymin>48.970588235294116</ymin>
      <xmax>161.66666666666669</xmax>
      <ymax>124.41176470588235</ymax>
    </bndbox>
  </object>
  <object>
    <name>bucket</name>
    <pose>Unspecified</pose>
    <truncated>0</truncated>
    <difficult>0</difficult>
    <bndbox>
      <xmin>166.00000000000003</xmin>
      <ymin>48.639705882352935</ymin>
      <xmax>216</xmax>
      <ymax>110.84558823529412</ymax>
    </bndbox>
  </object>
</annotation>
