<annotation>
  <folder>bucket-dataset</folder>
  <filename>00667.jpg</filename>
  <size>
    <width>240</width>
    <height>180</height>
    <depth>3</depth>
  </size>
  <segmented>0</segmented>
  <object>
    <name>bucket</name>
    <pose>Unspecified</pose>
    <truncated>0</truncated>
    <difficult>0</difficult>
    <bndbox>
      <xmin>41.166666666666664</xmin>
      <ymin>62.53676470588235</ymin>
      <xmax>80.83333333333333</xmax>
      <ymax>112.83088235294116</ymax>
    </bndbox>
  </object>
  <object>
    <name>bucket</name>
    <pose>Unspecified</pose>
    <truncated>0</truncated>
    <difficult>0</difficult>
    <bndbox>
      <xmin>84.83333333333333</xmin>
      <ymin>60.5514705882353</ymin>
      <xmax>130.83333333333331</xmax>
      <ymax>124.74264705882354</ymax>
    </bndbox>
  </object>
  <object>
    <name>bucket</name>
    <pose>Unspecified</pose>
    <truncated>0</truncated>
    <difficult>0</difficult>
    <bndbox>
      <xmin>128.5</xmin>
      <ymin>63.529411764705884</ymin>
      <xmax>171.83333333333334</xmax>
      <ymax>120.77205882352942</ymax>
    </bndbox>
  </object>
</annotation>
