<annotation>
  <folder>bucket-dataset</folder>
  <filename>00428.jpg</filename>
  <size>
    <width>240</width>
    <height>180</height>
    <depth>3</depth>
  </size>
  <segmented>0</segmented>
  <object>
    <name>bucket</name>
    <pose>Unspecified</pose>
    <truncated>0</truncated>
    <difficult>0</difficult>
    <bndbox>
      <xmin>21.666666666666664</xmin>
      <ymin>51.61764705882353</ymin>
      <xmax>65</xmax>
      <ymax>104.88970588235294</ymax>
    </bndbox>
  </object>
  <object>
    <name>bucket</name>
    <pose>Unspecified</pose>
    <truncated>0</truncated>
    <difficult>0</difficult>
    <bndbox>
      <xmin>65.33333333333333</xmin>
      <ymin>57.24264705882353</ymin>
      <xmax>96.66666666666666</xmax>
      <ymax>100.58823529411765</ymax>
    </bndbox>
  </object>
</annotation>
